setup.cfg
setup.py
ph_py/__init__.py
ph_py/error.py
ph_py/helpers.py
ph_py/product_hunt_client.py
ph_py.egg-info/PKG-INFO
ph_py.egg-info/SOURCES.txt
ph_py.egg-info/dependency_links.txt
ph_py.egg-info/requires.txt
ph_py.egg-info/top_level.txt
ph_py/models/__init__.py
ph_py/models/comment.py
ph_py/models/notification.py
ph_py/models/post.py
ph_py/models/related_link.py
ph_py/models/user.py
ph_py/models/user_details.py
ph_py/models/vote.py