Metadata-Version: 1.1
Name: ph-py
Version: 0.1
Summary: Product Hunt Beta Python Library
Home-page: https://github.com/anatg/ph_py
Author: Anat Gilboa and Jasdev Singh
Author-email: UNKNOWN
License: MIT
Keywords: api,product,hunt,product hunt
Platform: UNKNOWN
Classifier: Development Status :: 4 - Beta
Classifier: Intended Audience :: Developers
Classifier: License :: OSI Approved :: MIT License
Classifier: Programming Language :: Python :: 2.7
Classifier: Programming Language :: Python :: 3
Classifier: Programming Language :: Python :: 3.2
Classifier: Programming Language :: Python :: 3.3
Classifier: Programming Language :: Python :: 3.4
